{
	"name": "Amulet of Health",
	"type": "equipment",
	"folder": "4LH1C1GgngokUy8S",
	"img": "icons/equipment/neck/pendant-faceted-red.webp",
	"system": {
		"activities": {},
		"uses": {
			"spent": 0,
			"recovery": [],
			"max": ""
		},
		"description": {
			"value": "<p>Wondrous Item - Rare (Requires Attunement)</p><p><strong>Buff</strong></p><ul><li><p>Your &amp;reference[Constitution] score becomes 19 while you wear this amulet.</p></li><li><p>This has no effect if your Constitution is already 19 or higher.</p></li></ul>",
			"chat": ""
		},
		"identifier": "amulet-of-health",
		"source": {
			"revision": 1,
			"rules": "2024",
			"license": "",
			"book": "",
			"page": "",
			"custom": ""
		},
		"identified": true,
		"unidentified": {
			"description": "",
			"name": "Unidentified Amulet"
		},
		"container": null,
		"quantity": 1,
		"weight": {
			"value": 0.1,
			"units": "lb"
		},
		"price": {
			"value": 4000,
			"denomination": "gp"
		},
		"rarity": "rare",
		"attunement": "required",
		"attuned": false,
		"equipped": false,
		"armor": {
			"value": null,
			"magicalBonus": null,
			"dex": null
		},
		"cover": null,
		"crewed": false,
		"hp": {
			"value": null,
			"max": null,
			"dt": null,
			"conditions": ""
		},
		"type": {
			"value": "wondrous",
			"baseItem": ""
		},
		"properties": [
			"mgc"
		],
		"strength": null,
		"proficient": null
	},
	"effects": [
		{
			"name": "Amulet of Health",
			"img": "icons/equipment/neck/pendant-faceted-red.webp",
			"_id": "ObtXWapsou2jYoip",
			"type": "base",
			"system": {},
			"changes": [
				{
					"key": "system.abilities.con.value",
					"mode": 4,
					"value": "19",
					"priority": 40
				}
			],
			"disabled": false,
			"duration": {
				"startTime": null,
				"seconds": null,
				"combat": null,
				"rounds": null,
				"turns": null,
				"startRound": null,
				"startTurn": null
			},
			"description": "",
			"origin": "Compendium.elkan5e.elkan5e-magic-items.Item.xKJcsasjeJPHKyPm",
			"tint": "#ffffff",
			"transfer": true,
			"statuses": [],
			"flags": {
				"dae": {
					"disableCondition": "",
					"stackable": "noneName",
					"showIcon": false,
					"disableIncapacitated": false,
					"durationExpression": "",
					"macroRepeat": "none",
					"specialDuration": []
				},
				"ActiveAuras": {
					"isAura": false,
					"aura": "All",
					"nameOverride": "",
					"radius": "",
					"alignment": "",
					"type": "",
					"customCheck": "",
					"ignoreSelf": false,
					"height": false,
					"hidden": false,
					"displayTemp": false,
					"hostile": false,
					"onlyOnce": false,
					"wallsBlock": "system",
					"statuses": []
				}
			},
			"_key": "!items.effects!xKJcsasjeJPHKyPm.ObtXWapsou2jYoip"
		}
	],
	"_id": "xKJcsasjeJPHKyPm",
	"_key": "!items!xKJcsasjeJPHKyPm"
}