{
  "name": "Spell Lists",
  "type": "feat",
  "img": "icons/sundries/books/book-open-purple.webp",
  "system": {
    "description": {
      "value": "<p>Class Spell Lists</p><p>@UUID[Compendium.elkan5e.elkan5e-rules.JournalEntry.vaLYevRxKe8mAvdE.JournalEntryPage.bOMm72Xmest4hBy4]{Bard}</p><p>@UUID[Compendium.elkan5e.elkan5e-rules.JournalEntry.vaLYevRxKe8mAvdE.JournalEntryPage.POm2RctcMrK11sTq]{Cleric}</p><p>@UUID[Compendium.elkan5e.elkan5e-rules.JournalEntry.vaLYevRxKe8mAvdE.JournalEntryPage.816dAxycI1cXYrCa]{Druid}</p><p>@UUID[Compendium.elkan5e.elkan5e-rules.JournalEntry.vaLYevRxKe8mAvdE.JournalEntryPage.KewWBKn532POzyW4]{Paladin}</p><p>@UUID[Compendium.elkan5e.elkan5e-rules.JournalEntry.vaLYevRxKe8mAvdE.JournalEntryPage.lAhMRphO3T6NphaH]{Ranger}</p><p>@UUID[Compendium.elkan5e.elkan5e-rules.JournalEntry.vaLYevRxKe8mAvdE.JournalEntryPage.AhDBGnMKm7VqbOzs]{Sorcerer}</p><p>@UUID[Compendium.elkan5e.elkan5e-rules.JournalEntry.vaLYevRxKe8mAvdE.JournalEntryPage.eIAPSko797Cjf0Yb]{Warlock}</p><p>@UUID[Compendium.elkan5e.elkan5e-rules.JournalEntry.vaLYevRxKe8mAvdE.JournalEntryPage.MNWLud81msaiZukw]{Wizard}</p><p></p><p>Spells by School</p><p>@UUID[Compendium.elkan5e.elkan5e-rules.JournalEntry.MQixQwPAnbjydC5D.JournalEntryPage.fRctuS2C1P30zjAO]{Abjuration Spells}</p><p>@UUID[Compendium.elkan5e.elkan5e-rules.JournalEntry.MQixQwPAnbjydC5D.JournalEntryPage.D2ovyzg8yEFPPFRx]{Conjuration Spells}</p><p>@UUID[Compendium.elkan5e.elkan5e-rules.JournalEntry.MQixQwPAnbjydC5D.JournalEntryPage.ppulpuqZdX9NWhDW]{Divination Spells}</p><p>@UUID[Compendium.elkan5e.elkan5e-rules.JournalEntry.MQixQwPAnbjydC5D.JournalEntryPage.HNaA5EPd5oQbjpCS]{Enchantment Spells}</p><p>@UUID[Compendium.elkan5e.elkan5e-rules.JournalEntry.MQixQwPAnbjydC5D.JournalEntryPage.59py3wilfbmPlYOp]{Evocation Spells}</p><p>@UUID[Compendium.elkan5e.elkan5e-rules.JournalEntry.MQixQwPAnbjydC5D.JournalEntryPage.FXtdLPYZwF7jbrgX]{Illusion Spells}</p><p>@UUID[Compendium.elkan5e.elkan5e-rules.JournalEntry.MQixQwPAnbjydC5D.JournalEntryPage.NIhSGdIUiNhPd11A]{Necromancy Spells}</p><p>@UUID[Compendium.elkan5e.elkan5e-rules.JournalEntry.MQixQwPAnbjydC5D.JournalEntryPage.unhaExaZiVj3FqEl]{Transmutation Spells}</p>",
      "chat": ""
    },
    "source": {
      "custom": "elkan5e.com/spell-lists",
      "rules": "",
      "revision": 1,
      "book": "",
      "page": "",
      "license": ""
    },
    "uses": {
      "max": "",
      "spent": 0,
      "recovery": []
    },
    "type": {
      "value": "",
      "subtype": ""
    },
    "requirements": "",
    "identifier": "",
    "activities": {},
    "enchant": {},
    "prerequisites": {
      "level": null
    },
    "properties": []
  },
  "effects": [],
  "ownership": {
    "default": 0,
    "WaiirYzq9mhRj9cS": 3,
    "vHqSHJMdmEO6Mk2C": 3
  },
  "flags": {
    "core": {
      "sourceId": "Item.cHsd56xrUr4Ld2FE"
    },
    "midiProperties": {
      "confirmTargets": "default",
      "autoFailFriendly": false,
      "autoSaveFriendly": false,
      "critOther": false,
      "offHandWeapon": false,
      "magicdam": false,
      "magiceffect": false,
      "concentration": false,
      "noConcentrationCheck": false,
      "toggleEffect": false,
      "ignoreTotalCover": false,
      "idr": false,
      "idi": false,
      "idv": false,
      "ida": false
    },
    "midi-qol": {
      "effectActivation": false,
      "itemCondition": "",
      "reactionCondition": "",
      "otherCondition": "",
      "effectCondition": "",
      "rollAttackPerTarget": "default",
      "AoETargetType": "any",
      "AoETargetTypeIncludeSelf": true,
      "autoTarget": "default",
      "removeAttackDamageButtons": "default"
    },
    "tidy5e-sheet": {
      "section": "",
      "actionSection": ""
    }
  },
  "_stats": {
    "compendiumSource": "Item.cHsd56xrUr4Ld2FE",
    "duplicateSource": null,
    "coreVersion": "12.331",
    "systemId": "dnd5e",
    "systemVersion": "4.3.3",
    "createdTime": 1726952206395,
    "modifiedTime": 1740467419993,
    "lastModifiedBy": "ymGs3J4QpWbCOXON"
  },
  "folder": null,
  "sort": 0,
  "_id": "wzrkBadn8qx3zZrL",
  "_key": "!items!wzrkBadn8qx3zZrL"
}
