{
  "folder": "ffeQiNj6aEwjamZq",
  "name": "Shadowdancer",
  "type": "subclass",
  "_id": "wbxMlrL38E9Tfewu",
  "img": "icons/equipment/head/hood-cloth-blue-white.webp",
  "system": {
    "description": {
      "value": "<p>Shadowdancers train to manipulate shadows, even transforming themself into shadow to travel through darkness and strike at their foes. They weave magic spells using wisps of magical shadow they draw out of their surroundings. Shadowdancers are often members of secretive organizations, including intelligence agencies, assassin guilds, and hidden cults.</p><table class=\"features-table\" data-toc-level=\"3\" style=\"text-align:left\"><caption style=\"text-align:center\">The Shadowdancer</caption><colgroup><col class=\"level\" style=\"text-align:left;padding-right:10px;min-width:50px\"></col><col class=\"features\" style=\"text-align:left\"></col></colgroup><thead><tr><th scope=\"col\" style=\"text-align:left;padding:5px\">Level</th><th scope=\"col\" style=\"text-align:left;padding:5px\">Features</th></tr></thead><tbody><tr><td style=\"padding:5px\">3</td><td style=\"padding:5px\">@UUID[Compendium.elkan5e.elkan5e-class-features.Item.PfakcO5lEiPbsaun]{Eyes of Shade}, @UUID[Compendium.elkan5e.elkan5e-class-features.Item.7Gnq3qfLzpIuRs0U]{Meld with Shadows}</td></tr><tr><td style=\"padding:5px\">6</td><td style=\"padding:5px\">@UUID[Compendium.elkan5e.elkan5e-spells.Item.F1OXrcqeSVW4QJsO]{Darkness [Shadow Casting]}, @UUID[Compendium.elkan5e.elkan5e-spells.Item.865Z7wQrflrDk445]{Pass without Trace [Shadow Casting]}, @UUID[Compendium.elkan5e.elkan5e-spells.Item.kn8N0utJOjohpYmh]{Shadow Strike [Shadow Casting]}</td></tr><tr><td style=\"padding:5px\">10</td><td style=\"padding:5px\">@UUID[Compendium.elkan5e.elkan5e-class-features.Item.Z1WevTWQhrRwwyp8]{Hijack Shadow}, @UUID[Compendium.elkan5e.elkan5e-class-features.Item.SXI9iC2kLWjtlYmp]{Shadow Form}</td></tr><tr><td style=\"padding:5px\">14</td><td style=\"padding:5px\">@UUID[Compendium.elkan5e.elkan5e-class-features.Item.6Vq7as8e3VfMLFQo]{Shadow Stalker}</td></tr></tbody></table>",
      "chat": ""
    },
    "source": {
      "custom": "https://www.elkan5e.com/monk",
      "rules": "",
      "revision": 1,
      "book": "",
      "page": "",
      "license": ""
    },
    "identifier": "",
    "classIdentifier": "monk",
    "advancement": [
      {
        "_id": "hUOuOTrs6VXyxDZd",
        "type": "ItemGrant",
        "configuration": {
          "items": [
            {
              "uuid": "Compendium.elkan5e.elkan5e-class-features.Item.PfakcO5lEiPbsaun",
              "optional": false
            },
            {
              "uuid": "Compendium.elkan5e.elkan5e-class-features.Item.7Gnq3qfLzpIuRs0U",
              "optional": false
            }
          ],
          "optional": false,
          "spell": null
        },
        "value": {},
        "level": 3,
        "title": "Shadowdancer Features",
        "icon": null
      },
      {
        "_id": "jDbqGZ3jTXpprT4o",
        "type": "ItemGrant",
        "configuration": {
          "items": [
            {
              "uuid": "Compendium.elkan5e.elkan5e-spells.Item.F1OXrcqeSVW4QJsO",
              "optional": false
            },
            {
              "uuid": "Compendium.elkan5e.elkan5e-spells.Item.865Z7wQrflrDk445",
              "optional": false
            },
            {
              "uuid": "Compendium.elkan5e.elkan5e-spells.Item.kn8N0utJOjohpYmh",
              "optional": false
            }
          ],
          "optional": false,
          "spell": {
            "ability": [
              "wis"
            ],
            "preparation": "innate",
            "uses": {
              "max": "",
              "per": "",
              "requireSlot": false
            }
          }
        },
        "value": {},
        "level": 6,
        "title": "Shadow Casting",
        "icon": null
      },
      {
        "_id": "MjGRjt6rH00QwAoI",
        "type": "ItemGrant",
        "configuration": {
          "items": [
            {
              "uuid": "Compendium.elkan5e.elkan5e-class-features.Item.Z1WevTWQhrRwwyp8",
              "optional": false
            },
            {
              "uuid": "Compendium.elkan5e.elkan5e-class-features.Item.SXI9iC2kLWjtlYmp",
              "optional": false
            }
          ],
          "optional": false,
          "spell": null
        },
        "value": {},
        "level": 10,
        "title": "Shadowdancer Features",
        "icon": null
      },
      {
        "_id": "7vGAAvXb7mjEUh4B",
        "type": "ItemGrant",
        "configuration": {
          "items": [
            {
              "uuid": "Compendium.elkan5e.elkan5e-class-features.Item.6Vq7as8e3VfMLFQo",
              "optional": false
            }
          ],
          "optional": false,
          "spell": null
        },
        "value": {},
        "level": 14,
        "title": "Shadowdancer Feature",
        "icon": null
      }
    ],
    "spellcasting": {
      "progression": "none",
      "ability": "",
      "preparation": {
        "formula": ""
      }
    }
  },
  "effects": [],
  "sort": 0,
  "ownership": {
    "default": 0,
    "ymGs3J4QpWbCOXON": 3,
    "vHqSHJMdmEO6Mk2C": 3
  },
  "flags": {},
  "_stats": {
    "compendiumSource": null,
    "duplicateSource": null,
    "coreVersion": "12.331",
    "systemId": "dnd5e",
    "systemVersion": "4.3.8",
    "createdTime": 1726952201263,
    "modifiedTime": 1744082315682,
    "lastModifiedBy": "3Yi0HjF4PKCA4vX0"
  },
  "_key": "!items!wbxMlrL38E9Tfewu"
}
