{
    "folder": "hs1kzC3J5ULWhDl5",
    "name": "Attuned to Dreams",
    "type": "feat",
    "_id": "buu1JEDnE2J85BY7",
    "img": "icons/magic/time/day-night-sunset-sunrise.webp",
    "system": {
        "description": {
            "value": "<p>You are immune to magic that would put you to sleep, and you are always lucid while dreaming, allowing you to detect creatures entering your dreams or attempting to influence you while asleep.</p>",
            "chat": ""
        },
        "source": {
            "custom": "elkan5e.com/ancestrybackground",
            "rules": "",
            "revision": 1,
            "book": "Elkan 5e",
            "page": "",
            "license": ""
        },
        "uses": {
            "max": "",
            "spent": 0,
            "recovery": []
        },
        "type": {
            "value": "race",
            "subtype": ""
        },
        "requirements": "Brass Dragonborn",
        "properties": [],
        "identifier": "",
        "activities": {},
        "enchant": {},
        "prerequisites": {
            "level": null
        }
    },
    "effects": [],
    "sort": 350000,
    "ownership": {
        "default": 0,
        "ymGs3J4QpWbCOXON": 3,
        "9B4LXF0S1sIudaRa": 3,
        "vHqSHJMdmEO6Mk2C": 3
    },
    "flags": {
        "midiProperties": {
            "confirmTargets": "default",
            "autoFailFriendly": false,
            "autoSaveFriendly": false,
            "critOther": false,
            "offHandWeapon": false,
            "magicdam": false,
            "magiceffect": false,
            "concentration": false,
            "noConcentrationCheck": false,
            "toggleEffect": false,
            "ignoreTotalCover": false,
            "idr": false,
            "idi": false,
            "idv": false,
            "ida": false
        },
        "midi-qol": {
            "rollAttackPerTarget": "default",
            "itemCondition": "",
            "effectCondition": "",
            "reactionCondition": ""
        }
    },
    "_stats": {
        "compendiumSource": null,
        "duplicateSource": null,
        "coreVersion": "12.331",
        "systemId": "dnd5e",
        "systemVersion": "4.0.3",
        "createdTime": 1726952222510,
        "modifiedTime": 1730174773604,
        "lastModifiedBy": "YxlXl9sauSuWxHdZ"
    },
    "_key": "!items!buu1JEDnE2J85BY7"
}