{
	"folder": "eazGA4ZD48w7Dmiw",
	"name": "Aspect of the Mountain",
	"type": "feat",
	"_id": "ZjwzAnYRuWqTki1e",
	"img": "icons/environment/wilderness/cave-entrance-mountain.webp",
	"system": {
		"activities": {},
		"uses": {
			"spent": 0,
			"recovery": [],
			"max": ""
		},
		"description": {
			"value": "<p><em>You take on the power of the mountains, becoming more like the natural and magical creatures who inhabit the land you protect.</em></p><p>You gain the following benefits:</p><ul><li><p>You gain a &amp;reference[tremorsense] of 60 ft., allowing you to detect creatures by the vibrations they make in the earth.</p></li><li><p>You are immune to the &amp;reference[petrified apply=false] condition.</p></li><li><p>You can cast <em>@UUID[Compendium.elkan5e.elkan5e-spells.Item.l3PBmfstaAN5ybn3]{Meld Into Stone}</em> as a 3rd level spell without expending a spell slot.</p></li><li><p>You gain a burrowing speed of 5 ft. If you already have one, your burrowing speed increases by 5 ft.</p></li></ul>",
			"chat": ""
		},
		"identifier": "aspect-of-the-mountain",
		"source": {
			"revision": 1,
			"rules": "",
			"book": "Elkan 5e",
			"page": "",
			"custom": "elkan5e.com/druid",
			"license": ""
		},
		"enchant": {},
		"type": {
			"value": "subclass",
			"subtype": ""
		},
		"prerequisites": {
			"level": null
		},
		"properties": [],
		"requirements": "Earthshaker 14"
	},
	"effects": [
		{
			"name": "Aspect of the Mountain",
			"img": "icons/svg/aura.svg",
			"_id": "jBSF4BE1R9gj11iC",
			"type": "base",
			"system": {},
			"changes": [
				{
					"key": "ATL.detectionModes.feelTremor.range",
					"mode": 4,
					"value": "60",
					"priority": 20
				},
				{
					"key": "system.attributes.movement.burrow",
					"mode": 2,
					"value": "+5",
					"priority": 20
				}
			],
			"disabled": false,
			"duration": {
				"startTime": null,
				"seconds": null,
				"combat": null,
				"rounds": null,
				"turns": null,
				"startRound": null,
				"startTurn": null
			},
			"description": "",
			"origin": "Compendium.elkan5e.elkan5e-class-features.Item.ZjwzAnYRuWqTki1e",
			"tint": "#ffffff",
			"transfer": true,
			"statuses": [],
			"flags": {
				"dae": {
					"disableCondition": "",
					"disableIncapacitated": false,
					"stackable": "noneName",
					"showIcon": false,
					"durationExpression": "",
					"macroRepeat": "none",
					"specialDuration": []
				},
				"ActiveAuras": {
					"isAura": false,
					"aura": "None",
					"nameOverride": "",
					"radius": "",
					"alignment": "",
					"type": "",
					"customCheck": "",
					"ignoreSelf": false,
					"height": false,
					"hidden": false,
					"displayTemp": false,
					"hostile": false,
					"onlyOnce": false,
					"wallsBlock": "system"
				}
			},
			"_key": "!items.effects!ZjwzAnYRuWqTki1e.jBSF4BE1R9gj11iC"
		}
	],
	"flags": {
		"midiProperties": {
			"confirmTargets": "default",
			"autoFailFriendly": false,
			"autoSaveFriendly": false,
			"critOther": false,
			"offHandWeapon": false,
			"magicdam": false,
			"magiceffect": false,
			"noConcentrationCheck": false,
			"toggleEffect": false,
			"ignoreTotalCover": false,
			"idr": false,
			"idi": false,
			"idv": false,
			"ida": false
		},
		"midi-qol": {
			"rollAttackPerTarget": "default",
			"itemCondition": "",
			"reactionCondition": "",
			"effectCondition": "",
			"removeAttackDamageButtons": "default",
			"otherCondition": ""
		}
	},
	"_key": "!items!ZjwzAnYRuWqTki1e"
}