{
	"name": "Takatic Hard Leather",
	"type": "equipment",
	"img": "icons/equipment/chest/breastplate-layered-leather-blue.webp",
	"effects": [
		{
			"_id": "m3rmogg90aeydr2a",
			"changes": [],
			"disabled": false,
			"duration": {
				"startTime": null,
				"seconds": null,
				"combat": null,
				"rounds": null,
				"turns": null,
				"startRound": null,
				"startTurn": null
			},
			"origin": "Actor.rMccgdKBBCNbWd8m.Item.TlpMwUbRwDpePZ9R",
			"transfer": true,
			"flags": {
				"dae": {
					"stackable": "none",
					"durationExpression": "",
					"macroRepeat": "none",
					"specialDuration": [],
					"transfer": true
				},
				"dnd5e-helpers": {
					"rest-effect": "Ignore"
				},
				"ActiveAuras": {
					"isAura": false,
					"aura": "None",
					"radius": null,
					"alignment": "",
					"type": "",
					"ignoreSelf": false,
					"height": false,
					"hidden": false,
					"displayTemp": false,
					"hostile": false,
					"onlyOnce": false
				}
			},
			"tint": "#ffffff",
			"name": "Takatic Hard Leather",
			"description": "",
			"statuses": [],
			"img": "icons/equipment/chest/breastplate-layered-leather-blue.webp",
			"type": "base",
			"system": {},
			"_key": "!items.effects!JHHB84Lpo2vtfCJb.m3rmogg90aeydr2a"
		}
	],
	"folder": "K5xsW4FLQleQsk3D",
	"flags": {
		"midiProperties": {
			"confirmTargets": "default",
			"autoFailFriendly": false,
			"autoSaveFriendly": false,
			"critOther": false,
			"offHandWeapon": false,
			"magicdam": false,
			"magiceffect": false,
			"noConcentrationCheck": false,
			"toggleEffect": false,
			"ignoreTotalCover": false
		},
		"midi-qol": {
			"rollAttackPerTarget": "default",
			"itemCondition": "",
			"effectCondition": ""
		}
	},
	"system": {
		"description": {
			"value": "<p><em>This armor was intended for sailors, and is a bit oily to the touch. The armor is buoyant, created using a magical technique was developed by marines in Takat.</em></p><p>This armor floats to the surface of any body of water, lifting either a creature wearing it or an object tied to it. The armor can lift up to 250 pounds 20 ft. upwards through water at the beginning of each of the wearer's turns (or initiative count 10 if not worn by a creature).</p>",
			"chat": ""
		},
		"source": {
			"rules": "",
			"revision": 1,
			"book": "Elkan 5e",
			"page": "",
			"license": ""
		},
		"quantity": 1,
		"weight": {
			"value": 6,
			"units": "lb"
		},
		"price": {
			"value": 145,
			"denomination": "gp"
		},
		"attunement": "",
		"equipped": false,
		"rarity": "common",
		"identified": true,
		"cover": null,
		"crewed": false,
		"uses": {
			"max": "",
			"spent": 0,
			"recovery": []
		},
		"armor": {
			"value": 12,
			"dex": null,
			"magicalBonus": null
		},
		"hp": {
			"value": 0,
			"max": 0,
			"dt": null,
			"conditions": ""
		},
		"speed": {
			"value": null,
			"conditions": ""
		},
		"strength": null,
		"proficient": null,
		"properties": [],
		"identifier": "takatic-hard-leather",
		"unidentified": {
			"description": "<p><em><strong>Unidentified</strong></em></p><p><em>This armor was intended for sailors, and is a bit oily to the touch. The armor is buoyant, created using a magical technique was developed by marines in Takat.</em></p><p>This armor floats to the surface of any body of water, lifting either a creature wearing it or an object tied to it. The armor can lift up to 250 pounds 20 ft. upwards through water at the beginning of each of the wearer's turns (or initiative count 10 if not worn by a creature).</p>",
			"name": "Unidentified Takatic Hard Leather"
		},
		"type": {
			"value": "light",
			"baseItem": "leather"
		},
		"activities": {},
		"container": null,
		"attuned": false
	},
	"_id": "JHHB84Lpo2vtfCJb",
	"_key": "!items!JHHB84Lpo2vtfCJb"
}