{
	"name": "Divine Awareness",
	"type": "feat",
	"img": "icons/magic/perception/third-eye-blue-red.webp",
	"system": {
		"description": {
			"value": "<p>The [[lookup @name lowercase]] knows if it hears a lie.</p>",
			"chat": ""
		},
		"source": {
			"custom": "",
			"book": "",
			"page": "",
			"license": "",
			"rules": "",
			"revision": 1
		},
		"uses": {
			"max": "",
			"spent": 0,
			"recovery": []
		},
		"type": {
			"value": "",
			"subtype": ""
		},
		"requirements": "",
		"properties": [],
		"activities": {},
		"enchant": {},
		"prerequisites": {
			"level": null
		},
		"identifier": "divine-awareness"
	},
	"effects": [],
	"_id": "YC_ModRIIIVW5rHI",
	"folder": "SRDFeature000001",
	"_key": "!items!YC_ModRIIIVW5rHI"
}