{
	"folder": "oeTj3mYde0WB3IYi",
	"name": "Strong Swimmer",
	"type": "feat",
	"img": "icons/magic/water/wave-water-blue.webp",
	"system": {
		"description": {
			"value": "<p>You have a swim speed equal to your walking speed. If you later gain a swim speed, you can replace this feat with a different level 1 feat.</p>",
			"chat": ""
		},
		"source": {
			"custom": "elkan5e.com/feats/strong-swimmer",
			"rules": "",
			"revision": 1,
			"book": "Elkan 5e",
			"page": "",
			"license": ""
		},
		"uses": {
			"max": "",
			"spent": 0,
			"recovery": []
		},
		"type": {
			"value": "feat",
			"subtype": ""
		},
		"requirements": "Feat (Level 1)",
		"properties": [],
		"identifier": "",
		"activities": {},
		"enchant": {},
		"prerequisites": {
			"level": null
		},
		"advancement": [
			{
				"_id": "aC5HuW1uXBe16dL0",
				"type": "AbilityScoreImprovement",
				"configuration": {
					"cap": 2,
					"fixed": {
						"str": 0,
						"dex": 0,
						"con": 0,
						"int": 0,
						"wis": 0,
						"cha": 0
					},
					"locked": [],
					"points": 2
				},
				"value": {
					"type": "asi"
				},
				"level": 0,
				"title": "",
				"hint": ""
			}
		]
	},
	"effects": [
		{
			"changes": [
				{
					"key": "system.attributes.movement.swim",
					"mode": 4,
					"value": "@attributes.movement.walk",
					"priority": 20
				}
			],
			"transfer": true,
			"_id": "fzKpCcgSQVK5Y9E8",
			"disabled": false,
			"duration": {
				"startTime": null,
				"seconds": null,
				"combat": null,
				"rounds": null,
				"turns": null,
				"startRound": null,
				"startTurn": null
			},
			"origin": "Compendium.elkan5e.elkan5e-feats.Item.R0iU0b2is9caAWoQ",
			"tint": "#ffffff",
			"name": "Strong Swimmer",
			"description": "",
			"statuses": [],
			"img": "icons/magic/water/wave-water-blue.webp",
			"type": "base",
			"system": {},
			"_key": "!items.effects!R0iU0b2is9caAWoQ.fzKpCcgSQVK5Y9E8"
		}
	],
	"_id": "R0iU0b2is9caAWoQ",
	"_key": "!items!R0iU0b2is9caAWoQ"
}