{
    "name": "Quivering Palm (Damage)",
    "type": "feat",
    "img": "icons/magic/symbols/rune-sigil-black-pink.webp",
    "effects": [
        {
            "_id": "1few7swrvd9syf53",
            "changes": [],
            "disabled": false,
            "duration": {
                "startTime": null,
                "seconds": null,
                "combat": null,
                "rounds": null,
                "turns": null,
                "startRound": null,
                "startTurn": null
            },
            "transfer": false,
            "flags": {
                "dae": {
                    "selfTarget": false,
                    "stackable": "none",
                    "durationExpression": "(@classes.monk.levels)d1*86400",
                    "macroRepeat": "none",
                    "specialDuration": [],
                    "transfer": false
                },
                "core": {
                    "statusId": ""
                },
                "ActiveAuras": {
                    "isAura": false,
                    "aura": "None",
                    "radius": null,
                    "alignment": "",
                    "type": "",
                    "ignoreSelf": false,
                    "height": false,
                    "hidden": false,
                    "displayTemp": false,
                    "hostile": false,
                    "onlyOnce": false
                }
            },
            "tint": "#ffffff",
            "name": "Ki: Quivering Palm",
            "description": "",
            "origin": null,
            "statuses": [],
            "_stats": {
                "compendiumSource": null,
                "duplicateSource": null,
                "coreVersion": "12.331",
                "systemId": "dnd5e",
                "systemVersion": "4.0.2",
                "createdTime": null,
                "modifiedTime": null,
                "lastModifiedBy": null
            },
            "img": "icons/magic/symbols/rune-sigil-black-pink.webp",
            "type": "base",
            "system": {},
            "sort": 0,
            "_key": "!items.effects!5KI5geHZpt6NIkyG.1few7swrvd9syf53"
        }
    ],
    "folder": "n1N4yw4iM9FB4BkF",
    "flags": {
        "core": {},
        "midi-qol": {
            "effectActivation": false,
            "removeAttackDamageButtons": "default",
            "rollAttackPerTarget": "default",
            "itemCondition": "",
            "effectCondition": ""
        },
        "midiProperties": {
            "nodam": false,
            "fulldam": false,
            "halfdam": false,
            "rollOther": false,
            "critOther": false,
            "magicdam": false,
            "magiceffect": true,
            "concentration": false,
            "toggleEffect": false,
            "autoFailFriendly": false,
            "autoSaveFriendly": false,
            "offHandWeapon": false,
            "ignoreTotalCover": false,
            "confirmTargets": "default",
            "saveDamage": "default",
            "noConcentrationCheck": false,
            "bonusSaveDamage": "default"
        },
        "dnd5e": {
            "riders": {
                "activity": [],
                "effect": []
            }
        }
    },
    "system": {
        "description": {
            "value": "<p><span style=\"font-weight:bold\" class=\"wixui-rich-text__text\"><strong>Action</strong></span>\u00a0- 1 Creature - Magical</p><p>The vibrations created by your @UUID[Compendium.elkan5e.elkan5e-class-features.Item.24aoMibvXzQenfBR]{Quivering Palm} are harmless unless you use your action to amplify them. To do so, you and the target must be within 1000 ft. of you. When you use this action, the vibrations end.</p><p><strong>Constitution Saving Throw</strong></p><p><strong>Failure:</strong> Target takes [[/damage 10d10 thunder]] damage.</p><p><strong>Success:</strong> Half damage.</p>",
            "chat": ""
        },
        "source": {
            "custom": "elkan5e.com/monk",
            "revision": 1,
            "rules": "",
            "book": "Elkan 5e",
            "page": "",
            "license": ""
        },
        "uses": {
            "max": "",
            "recovery": [],
            "spent": 0
        },
        "type": {
            "value": "subclass",
            "subtype": "ki"
        },
        "requirements": "Open Hand 14",
        "properties": [
            "mgc"
        ],
        "activities": {
            "dnd5eactivity000": {
                "_id": "dnd5eactivity000",
                "type": "save",
                "activation": {
                    "type": "action",
                    "value": 1,
                    "condition": "",
                    "override": false
                },
                "consumption": {
                    "targets": [],
                    "scaling": {
                        "allowed": false,
                        "max": ""
                    },
                    "spellSlot": true
                },
                "description": {
                    "chatFlavor": ""
                },
                "duration": {
                    "concentration": false,
                    "value": "",
                    "units": "",
                    "special": "",
                    "override": false
                },
                "effects": [
                    {
                        "_id": "1few7swrvd9syf53",
                        "onSave": false
                    }
                ],
                "range": {
                    "value": "1000",
                    "units": "ft",
                    "special": "",
                    "override": false
                },
                "target": {
                    "template": {
                        "count": "",
                        "contiguous": false,
                        "type": "",
                        "size": "",
                        "width": "",
                        "height": "",
                        "units": ""
                    },
                    "affects": {
                        "count": "1",
                        "type": "creature",
                        "choice": false,
                        "special": ""
                    },
                    "prompt": true,
                    "override": false
                },
                "uses": {
                    "spent": 0,
                    "max": "",
                    "recovery": []
                },
                "damage": {
                    "onSave": "half",
                    "parts": [
                        {
                            "number": 10,
                            "denomination": 10,
                            "bonus": "",
                            "types": [
                                "thunder"
                            ],
                            "custom": {
                                "enabled": false,
                                "formula": ""
                            },
                            "scaling": {
                                "mode": "whole",
                                "number": null,
                                "formula": ""
                            }
                        }
                    ]
                },
                "save": {
                    "ability": "con",
                    "dc": {
                        "calculation": "wis",
                        "formula": ""
                    }
                },
                "sort": 0
            }
        },
        "identifier": "",
        "enchant": {},
        "prerequisites": {
            "level": null
        }
    },
    "ownership": {
        "default": 0,
        "ymJDAw0PgXIWIHMH": 3,
        "ymGs3J4QpWbCOXON": 3,
        "vHqSHJMdmEO6Mk2C": 3
    },
    "_stats": {
        "compendiumSource": null,
        "duplicateSource": null,
        "coreVersion": "12.331",
        "systemId": "dnd5e",
        "systemVersion": "4.0.2",
        "createdTime": 1726952007299,
        "modifiedTime": 1726952007299,
        "lastModifiedBy": "vHqSHJMdmEO6Mk2C"
    },
    "_id": "5KI5geHZpt6NIkyG",
    "sort": 0,
    "_key": "!items!5KI5geHZpt6NIkyG"
}