{
  "_id": "eXTDHstQ4bsmPgNh",
  "name": "Witch Sight",
  "type": "feat",
  "img": "icons/magic/perception/eye-tendrils-web-purple.webp",
  "effects": [],
  "folder": "pav7UEPiuGgBB9pL",
  "sort": 300000,
  "flags": {
    "core": {
      "sourceId": "Compendium.dnd5e.classfeatures.snsjxGfmzWfZR5Nh"
    },
    "midiProperties": {
      "confirmTargets": "default",
      "autoFailFriendly": false,
      "autoSaveFriendly": false,
      "critOther": false,
      "offHandWeapon": false,
      "magicdam": false,
      "magiceffect": false,
      "concentration": false,
      "noConcentrationCheck": false,
      "toggleEffect": false,
      "ignoreTotalCover": false,
      "idr": false,
      "idi": false,
      "idv": false,
      "ida": false
    },
    "midi-qol": {
      "rollAttackPerTarget": "default",
      "itemCondition": "",
      "effectCondition": "",
      "reactionCondition": ""
    }
  },
  "system": {
    "description": {
      "value": "<p>You can see the true form of any shapechanger or creature concealed by illusion or transmutation magic while the creature is within 30 feet of you and within line of sight.</p>",
      "chat": ""
    },
    "source": {
      "custom": "https://www.elkan5e.com/invocations/witch-sight",
      "rules": "",
      "revision": 1,
      "book": "",
      "page": "",
      "license": ""
    },
    "uses": {
      "max": "",
      "spent": 0,
      "recovery": []
    },
    "type": {
      "value": "class",
      "subtype": "eldritchInvocation"
    },
    "requirements": "Warlock 15",
    "properties": [
      "mgc"
    ],
    "prerequisites": {
      "level": 15
    },
    "identifier": "",
    "activities": {},
    "enchant": {}
  },
  "ownership": {
    "default": 0,
    "ymJDAw0PgXIWIHMH": 3,
    "vHqSHJMdmEO6Mk2C": 3
  },
  "_stats": {
    "compendiumSource": "Compendium.dnd5e.classfeatures.snsjxGfmzWfZR5Nh",
    "duplicateSource": null,
    "coreVersion": "12.331",
    "systemId": "dnd5e",
    "systemVersion": "4.0.2",
    "createdTime": 1726952014158,
    "modifiedTime": 1730160703760,
    "lastModifiedBy": "vY549pHXgrOzkh9H"
  },
  "_key": "!items!eXTDHstQ4bsmPgNh"
}
